{
  "Header": {
    "WolvenKitVersion": "8.14.0",
    "WKitJsonVersion": "0.0.8",
    "GameVersion": 2120,
    "DataType": "CR2W"
  },
  "Data": {
    "Version": 195,
    "BuildVersion": 0,
    "RootChunk": {
      "$type": "JsonResource",
      "cookingPlatform": "PLATFORM_PC",
      "root": {
        "HandleId": "0",
        "Data": {
          "$type": "localizationPersistenceSubtitleEntries",
          "entries": [
            {
              "$type": "localizationPersistenceSubtitleEntry",
              "femaleVariant": "Hey, V, hope it's not a bad time. Uh, some... news trickled down the ripper grapevine. Thought it might interest you.",
              "maleVariant": "",
              "stringId": "3367760839023915020"
            },
            {
              "$type": "localizationPersistenceSubtitleEntry",
              "femaleVariant": "Listen, V, you were only just here, I know. But I just got word of a juicy piece of news. Thought it might interest you.",
              "maleVariant": "",
              "stringId": "3367760841959927820"
            },
            {
              "$type": "localizationPersistenceSubtitleEntry",
              "femaleVariant": "Heh, well, some implant soft updates just hit the streets, completely fresh batch. Useful as hell, rippers say.",
              "maleVariant": "",
              "stringId": "3367760841959927828"
            },
            {
              "$type": "localizationPersistenceSubtitleEntry",
              "femaleVariant": "Update – where can I get it?",
              "maleVariant": "",
              "stringId": "3367760846305226752"
            },
            {
              "$type": "localizationPersistenceSubtitleEntry",
              "femaleVariant": "Hot tip – thanks, Vik. Now, how might one nab this wonder-update?",
              "maleVariant": "",
              "stringId": "3367760846355558408"
            },
            {
              "$type": "localizationPersistenceSubtitleEntry",
              "femaleVariant": "From just about every ripperdoc in town, actually. So not that much wonder at all, I'm afraid.",
              "maleVariant": "",
              "stringId": "3367760846355558416"
            },
            {
              "$type": "localizationPersistenceSubtitleEntry",
              "femaleVariant": "Cut the foreplay, Vik. Spill.",
              "maleVariant": "",
              "stringId": "3478196497009065984"
            },
            {
              "$type": "localizationPersistenceSubtitleEntry",
              "femaleVariant": "Dropped a dime to you first, 'cause, well, I'm rootin' for ya, kid. I'd love to see you get ahead of the pack.",
              "maleVariant": "",
              "stringId": "3478196881626742784"
            },
            {
              "$type": "localizationPersistenceSubtitleEntry",
              "femaleVariant": "What's in the update pack?",
              "maleVariant": "",
              "stringId": "3478201455112601600"
            },
            {
              "$type": "localizationPersistenceSubtitleEntry",
              "femaleVariant": "What's in the batch?",
              "maleVariant": "",
              "stringId": "3478201567436062720"
            },
            {
              "$type": "localizationPersistenceSubtitleEntry",
              "femaleVariant": "Y'know, system streamlining, new subroutines, expanded user settings... Eh, you'll need to see.",
              "maleVariant": "",
              "stringId": "3478202028406849536"
            },
            {
              "$type": "localizationPersistenceSubtitleEntry",
              "femaleVariant": "Oh, you can hook me up too.",
              "maleVariant": "",
              "stringId": "3478203553321566208"
            },
            {
              "$type": "localizationPersistenceSubtitleEntry",
              "femaleVariant": "Sure thing. Swing by anytime.",
              "maleVariant": "",
              "stringId": "3478213642317185024"
            },
            {
              "$type": "localizationPersistenceSubtitleEntry",
              "femaleVariant": "Can, indeed. As soon as you settle the tab you've run up.",
              "maleVariant": "",
              "stringId": "3478213829903237120"
            }
          ]
        }
      }
    },
    "EmbeddedFiles": []
  }
}