{
  "Header": {
    "WolvenKitVersion": "8.14.0",
    "WKitJsonVersion": "0.0.8",
    "GameVersion": 2120,
    "DataType": "CR2W"
  },
  "Data": {
    "Version": 195,
    "BuildVersion": 0,
    "RootChunk": {
      "$type": "JsonResource",
      "cookingPlatform": "PLATFORM_PC",
      "root": {
        "HandleId": "0",
        "Data": {
          "$type": "localizationPersistenceSubtitleEntries",
          "entries": [
            {
              "$type": "localizationPersistenceSubtitleEntry",
              "femaleVariant": "Чё?",
              "maleVariant": "",
              "stringId": "1625800325838770176"
            },
            {
              "$type": "localizationPersistenceSubtitleEntry",
              "femaleVariant": "Надо чего?",
              "maleVariant": "",
              "stringId": "1625800325872324608"
            },
            {
              "$type": "localizationPersistenceSubtitleEntry",
              "femaleVariant": "Твоя мамаша звонила, просила отправить тебя обратно в твой ёбаный клоповник.",
              "maleVariant": "",
              "stringId": "1625800325939433472"
            },
            {
              "$type": "localizationPersistenceSubtitleEntry",
              "femaleVariant": "Это не твоя территория. Уёбывай.",
              "maleVariant": "",
              "stringId": "1625800325956210688"
            },
            {
              "$type": "localizationPersistenceSubtitleEntry",
              "femaleVariant": "Или уберёшь это, или прям тут и сдохнешь.",
              "maleVariant": "",
              "stringId": "1625800326006542336"
            },
            {
              "$type": "localizationPersistenceSubtitleEntry",
              "femaleVariant": "Убери эту хуйню.",
              "maleVariant": "",
              "stringId": "1625800326023319552"
            },
            {
              "$type": "localizationPersistenceSubtitleEntry",
              "femaleVariant": "А сапогом в морду не хочешь?",
              "maleVariant": "",
              "stringId": "1625800326107205632"
            },
            {
              "$type": "localizationPersistenceSubtitleEntry",
              "femaleVariant": "Так-то, тварь.",
              "maleVariant": "Так-то, урод.",
              "stringId": "1625800326191091712"
            },
            {
              "$type": "localizationPersistenceSubtitleEntry",
              "femaleVariant": "Видишь, блядь, это несложно.",
              "maleVariant": "",
              "stringId": "1625800326207868928"
            },
            {
              "$type": "localizationPersistenceSubtitleEntry",
              "femaleVariant": "Что это было?",
              "maleVariant": "",
              "stringId": "1625800326291755008"
            },
            {
              "$type": "localizationPersistenceSubtitleEntry",
              "femaleVariant": "Э-э-э… Не понимаю…",
              "maleVariant": "",
              "stringId": "1625800326308532224"
            },
            {
              "$type": "localizationPersistenceSubtitleEntry",
              "femaleVariant": "Ох, я слишком стар для этого дерьма…",
              "maleVariant": "",
              "stringId": "1625800326425972736"
            },
            {
              "$type": "localizationPersistenceSubtitleEntry",
              "femaleVariant": "О-о-о, хуясе у меня приход…",
              "maleVariant": "",
              "stringId": "1625800326459527168"
            },
            {
              "$type": "localizationPersistenceSubtitleEntry",
              "femaleVariant": "Выкурить эту мразь!",
              "maleVariant": "",
              "stringId": "1625800326509858816"
            },
            {
              "$type": "localizationPersistenceSubtitleEntry",
              "femaleVariant": "Где эта сволочь?",
              "maleVariant": "",
              "stringId": "1625800326526636032"
            },
            {
              "$type": "localizationPersistenceSubtitleEntry",
              "femaleVariant": "Аргх, она ещё одного уложила!",
              "maleVariant": "Он ещё одного уложил!",
              "stringId": "1625800326576967680"
            },
            {
              "$type": "localizationPersistenceSubtitleEntry",
              "femaleVariant": "Ладно, ладно. Сейчас приду.",
              "maleVariant": "",
              "stringId": "1625800326627299328"
            },
            {
              "$type": "localizationPersistenceSubtitleEntry",
              "femaleVariant": "Мочи суку!",
              "maleVariant": "",
              "stringId": "1625800326711185408"
            },
            {
              "$type": "localizationPersistenceSubtitleEntry",
              "femaleVariant": "Сдохни, мразь!",
              "maleVariant": "Сдохни, ублюдок!",
              "stringId": "1625800326727962624"
            },
            {
              "$type": "localizationPersistenceSubtitleEntry",
              "femaleVariant": "Сюрприз, сука!",
              "maleVariant": "",
              "stringId": "1625800326778294272"
            },
            {
              "$type": "localizationPersistenceSubtitleEntry",
              "femaleVariant": "А-а-а… Нет… Пожалуйста…",
              "maleVariant": "",
              "stringId": "1625800326862180352"
            },
            {
              "$type": "localizationPersistenceSubtitleEntry",
              "femaleVariant": "Выебем её! А-а-а! Вперёд!",
              "maleVariant": "Выебем его! А-а-а! Вперёд!",
              "stringId": "1625800326929289216"
            },
            {
              "$type": "localizationPersistenceSubtitleEntry",
              "femaleVariant": "Покажите, кто тут зверь!",
              "maleVariant": "",
              "stringId": "1625800327013175296"
            },
            {
              "$type": "localizationPersistenceSubtitleEntry",
              "femaleVariant": "Пусть за всё заплатит!",
              "maleVariant": "",
              "stringId": "1625800327046729728"
            },
            {
              "$type": "localizationPersistenceSubtitleEntry",
              "femaleVariant": "Смотри, куда идёшь, милая.",
              "maleVariant": "Смотри, куда идёшь, милый.",
              "stringId": "1625800327113838592"
            },
            {
              "$type": "localizationPersistenceSubtitleEntry",
              "femaleVariant": "Ща получишь.",
              "maleVariant": "",
              "stringId": "1625800327130615808"
            },
            {
              "$type": "localizationPersistenceSubtitleEntry",
              "femaleVariant": "Да, что такое? Говори.",
              "maleVariant": "",
              "stringId": "1625800327180947456"
            },
            {
              "$type": "localizationPersistenceSubtitleEntry",
              "femaleVariant": "Ага… Да… Ну придумай что-нибудь…",
              "maleVariant": "",
              "stringId": "1625800327248056320"
            },
            {
              "$type": "localizationPersistenceSubtitleEntry",
              "femaleVariant": "Ну есть немного… Литр могу продать… Мало? Ну бля…",
              "maleVariant": "",
              "stringId": "1625800327264833536"
            },
            {
              "$type": "localizationPersistenceSubtitleEntry",
              "femaleVariant": "Сзади её обходи!",
              "maleVariant": "",
              "stringId": "1625800327382274048"
            },
            {
              "$type": "localizationPersistenceSubtitleEntry",
              "femaleVariant": "Есть!",
              "maleVariant": "",
              "stringId": "1625800327449382912"
            },
            {
              "$type": "localizationPersistenceSubtitleEntry",
              "femaleVariant": "У неё гранаты!",
              "maleVariant": "У него гранаты!",
              "stringId": "1625800327533268992"
            },
            {
              "$type": "localizationPersistenceSubtitleEntry",
              "femaleVariant": "Эй, ты, хуепутало. Я тебя за секунду порву!",
              "maleVariant": "",
              "stringId": "1625828485523410944"
            },
            {
              "$type": "localizationPersistenceSubtitleEntry",
              "femaleVariant": "Держись там, чумба…",
              "maleVariant": "",
              "stringId": "1625941729315491840"
            },
            {
              "$type": "localizationPersistenceSubtitleEntry",
              "femaleVariant": "Это чё такое?..",
              "maleVariant": "",
              "stringId": "1770908698174394368"
            },
            {
              "$type": "localizationPersistenceSubtitleEntry",
              "femaleVariant": "Выходи, поиграем!",
              "maleVariant": "",
              "stringId": "1770913883558875136"
            },
            {
              "$type": "localizationPersistenceSubtitleEntry",
              "femaleVariant": "Не упустите её!",
              "maleVariant": "Не упустите его!",
              "stringId": "1770914353304145920"
            },
            {
              "$type": "localizationPersistenceSubtitleEntry",
              "femaleVariant": "У нас, кажется, крыса…",
              "maleVariant": "",
              "stringId": "1771898546821632000"
            },
            {
              "$type": "localizationPersistenceSubtitleEntry",
              "femaleVariant": "В чём дело?",
              "maleVariant": "",
              "stringId": "1771898681962106880"
            },
            {
              "$type": "localizationPersistenceSubtitleEntry",
              "femaleVariant": "Ты! А ну-ка, проверь!",
              "maleVariant": "",
              "stringId": "1771898870571569152"
            },
            {
              "$type": "localizationPersistenceSubtitleEntry",
              "femaleVariant": "Э, я разве с тобой говорил?",
              "maleVariant": "",
              "stringId": "1959247411061760004"
            },
            {
              "$type": "localizationPersistenceSubtitleEntry",
              "femaleVariant": "Готова продолжить?",
              "maleVariant": "Готов продолжить?",
              "stringId": "1959247411128868864"
            },
            {
              "$type": "localizationPersistenceSubtitleEntry",
              "femaleVariant": "Давай побыстрей уже.",
              "maleVariant": "",
              "stringId": "1959247411145646084"
            }
          ]
        }
      }
    },
    "EmbeddedFiles": []
  }
}